{
  "data": [
    {
      "category": "테스트카테고리4",
      "bank": "테스트은행4",
      "date": "10",
      "amount": "84773",
      "done": false,
      "markedForDeletion": false,
      "excluded": false
    },
    {
      "category": "테스트카테고리1",
      "bank": "테스트은행4",
      "date": "13",
      "amount": "461639",
      "done": true,
      "markedForDeletion": false,
      "excluded": false
    },
    {
      "category": "테스트카테고리1",
      "bank": "테스트은행2",
      "date": "9",
      "amount": "299847",
      "done": false,
      "markedForDeletion": false,
      "excluded": false
    },
    {
      "category": "테스트카테고리2",
      "bank": "테스트은행5",
      "date": "5",
      "amount": "254908",
      "done": true,
      "markedForDeletion": false,
      "excluded": false
    },
    {
      "category": "테스트카테고리3",
      "bank": "테스트은행5",
      "date": "20",
      "amount": "294972",
      "done": false,
      "markedForDeletion": false,
      "excluded": false
    },
    {
      "category": "테스트카테고리3",
      "bank": "테스트은행2",
      "date": "2",
      "amount": "230517",
      "done": true,
      "markedForDeletion": false,
      "excluded": false
    },
    {
      "category": "테스트카테고리4",
      "bank": "테스트은행5",
      "date": "27",
      "amount": "486131",
      "done": false,
      "markedForDeletion": false,
      "excluded": false
    },
    {
      "category": "테스트카테고리1",
      "bank": "테스트은행4",
      "date": "28",
      "amount": "307763",
      "done": true,
      "markedForDeletion": false,
      "excluded": false
    },
    {
      "category": "테스트카테고리4",
      "bank": "테스트은행2",
      "date": "15",
      "amount": "62549",
      "done": true,
      "markedForDeletion": false,
      "excluded": false
    },
    {
      "category": "테스트카테고리1",
      "bank": "테스트은행5",
      "date": "26",
      "amount": "127742",
      "done": true,
      "markedForDeletion": false,
      "excluded": false
    }
  ],
  "sections": {
    "테스트카테고리1": "000-000-0001",
    "테스트카테고리2": "000-000-0002",
    "테스트카테고리3": "000-000-0003",
    "테스트카테고리4": "000-000-0004",
    "테스트카테고리5": "000-000-0005"
  }
}